README.md
setup.py
paypro/__init__.py
paypro/client.py
paypro/error.py
paypro/version.py
paypro.egg-info/PKG-INFO
paypro.egg-info/SOURCES.txt
paypro.egg-info/dependency_links.txt
paypro.egg-info/requires.txt
paypro.egg-info/top_level.txt
paypro/data/ca-bundle.crt