Metadata-Version: 1.1
Name: paypro
Version: 0.1.0
Summary: Client for PayPro API v1
Home-page: https://github.com/paypronl/paypro-python-v1
Author: PayPro
Author-email: development@paypro.nl
License: MIT
Keywords: paypro,payment,service
Platform: UNKNOWN
Classifier: Programming Language :: Python
Classifier: Programming Language :: Python :: 3
Classifier: Development Status :: 4 - Beta
Classifier: Intended Audience :: Developers
Classifier: License :: OSI Approved :: MIT License
Classifier: Operating System :: OS Independent
